dayabay_model/__init__.py
dayabay_model/model_dayabay.py
dayabay_model/model_dayabay.yaml
dayabay_model/bundles/refine_detector_data.py
dayabay_model/bundles/refine_lsnl_data.py
dayabay_model/bundles/refine_neutrino_rate_data.py
dayabay_model/bundles/sync_neutrino_rate_detector_data.py
dayabay_model/tools/__init__.py
dayabay_model/tools/validate_dataset.py
dayabay_model/tools/validate_load_array.py
dayabay_model-1.7.1.dist-info/licenses/LICENSE
dayabay_model-1.7.1.dist-info/METADATA
dayabay_model-1.7.1.dist-info/WHEEL
dayabay_model-1.7.1.dist-info/top_level.txt
dayabay_model-1.7.1.dist-info/RECORD
