Metadata-Version: 2.4
Name: dayabay-model
Version: 1.7.1
Summary: Model of the Daya Bay Reactor Neutrino Experiment for neutrino oscillation analysis based official data release.
Author-email: DAGModelling Team <dagflow@jinr.ru>
Maintainer-email: DAGModelling Team <dagflow@jinr.ru>
License-Expression: MIT
Project-URL: Bug Tracker, https://github.com/dayabay-experiment/dayabay-model/issues
Project-URL: documentation, https://github.com/dayabay-experiment/dayabay-model/wiki
Project-URL: homepage, https://github.com/dayabay-experiment/dayabay-model
Project-URL: repository, https://github.com/dayabay-experiment/dayabay-model
Classifier: Programming Language :: Python :: 3 :: Only
Classifier: Programming Language :: Python :: 3.11
Classifier: Programming Language :: Python :: 3.12
Classifier: Programming Language :: Python :: 3.13
Requires-Python: >=3.11
License-File: LICENSE
Requires-Dist: colorama
Requires-Dist: dgm-fit>=0.2
Requires-Dist: dgm-reactor-neutrino>=0.2.2
Requires-Dist: dayabay-data-official
Requires-Dist: more-itertools
Requires-Dist: semver
Provides-Extra: test
Requires-Dist: dgm-reactor-neutrino[test]>=0.2.2; extra == "test"
Requires-Dist: ipykernel; extra == "test"
Requires-Dist: ipython; extra == "test"
Requires-Dist: ipywidgets; extra == "test"
Requires-Dist: nbconvert; extra == "test"
Requires-Dist: parameterized; extra == "test"
Requires-Dist: pygraphviz; extra == "test"
Dynamic: license-file
